transdict-0.1b2.dist-info/zip-safe
transdict-0.1b2.dist-info/WHEEL
transdict-0.1b2.dist-info/METADATA
transdict-0.1b2.dist-info/metadata.json
transdict-0.1b2.dist-info/top_level.txt
transdict-0.1b2.dist-info/DESCRIPTION.rst
transdict-0.1b2.dist-info/RECORD
transdict/__init__.py
transdict/transdict.py
