Metadata-Version: 2.0
Name: transdict
Version: 0.1b2
Summary: Python dict mapping with transform functions
Home-page: https://github.com/golightlyb/transdict.py
Author: Tawesoft Ltd
Author-email: opensource@tawesoft.co.uk
License: GNU All-Permissive License
Platform: UNKNOWN
Classifier: Development Status :: 4 - Beta
Classifier: Intended Audience :: Developers
Classifier: License :: OSI Approved
Classifier: Programming Language :: Python :: 3
Classifier: Programming Language :: Python :: 3.4
Classifier: Topic :: Software Development :: Libraries :: Python Modules
